{
  "version_id": "tasmanian_legislation:2017-07-05/sr-2007-055",
  "type": "secondary_legislation",
  "jurisdiction": "tasmania",
  "source": "tasmanian_legislation",
  "citation": "Water Management (Dam Works Exemption) Order 2007 (Tas)",
  "url": "https://www.legislation.tas.gov.au/view/whole/html/inforce/current/sr-2007-055",
  "text": "Water Management (Dam Works Exemption) Order 2007\n\nI make the following order under section 137(2) of the Water Management Act 1999 .\n\n27 June 2007\n\nD. E. LLEWELLYN\n\nMinister for Primary Industries and Water\n\n1. Short title\n    This order may be cited as the Water Management (Dam Works Exemption) Order 2007 .\n\n2. Commencement\n    This order takes effect on 16 July 2007.\n\n3. Interpretation\n        (1) In this order –\n            Act means the Water Management Act 1999 .\n        (2) An expression used in this order that is defined in the Act has the same meaning as so defined.\n        (3) The Acts Interpretation Act 1931 applies to the interpretation of this order as if it were by-laws.\n\n4. Permit not required for certain dam works\n    A permit under Part 8 of the Act is not required in respect of dam works of a type specified in Schedule 1 if they are for a dam that is –\n            (a) used primarily for hydro-electric power generation; or\n            (b) part of a water storage scheme that has, as its primary purpose, hydro-electric power generation.\n\nSCHEDULE 1 - Dam works for which permit not required\n\nClause 4\n\n    1. Dam works for routine repairs &c.\n        Dam works that –\n                (a) are necessary to restore a dam's operational capacity or for its maintenance, routine repair, modification or upgrading; and\n                (b) do not –\n                        (i) alter the functionality of the dam's design or its specifications; or\n                        (ii) raise the full supply level of the associated reservoir; or\n                        (iii) involve the rebuilding of the dam; or\n                        (iv) cause environmental nuisance, material environmental harm or serious environmental harm; or\n                        (v) increase any risk to human life.\n    2. Urgent dam works\n        Dam works that –\n                (a) are urgently required to prevent injury to any person or damage to any dam; and\n                (b) do not cause serious environmental harm.\n\nDisplayed and numbered in accordance with the Rules Publication Act 1953.\n\nNotified in the Gazette on 4 July 2007\n\nThis order is administered in the Department of Primary Industries and Water.\n"
}