{
  "version_id": "tasmanian_legislation:2017-07-05/act-2007-072",
  "type": "primary_legislation",
  "jurisdiction": "tasmania",
  "source": "tasmanian_legislation",
  "citation": "Monetary Penalties Enforcement (Transitional Arrangements and Consequential Amendments) Act 2007 (Tas)",
  "url": "https://www.legislation.tas.gov.au/view/whole/html/inforce/current/act-2007-072",
  "text": "Monetary Penalties Enforcement (Transitional Arrangements and Consequential Amendments) Act 2007\n\nAn Act to amend the Monetary Penalties Enforcement Act 2005 and to amend certain Acts and statutory rules consequential on the enactment of that Act\n[Royal Assent 19 December 2007]\n\nBe it enacted by His Excellency the Governor of Tasmania, by and with the advice and consent of the Legislative Council and House of Assembly, in Parliament assembled, as follows:\n\n1. Short title\n    This Act may be cited as the Monetary Penalties Enforcement (Transitional Arrangements and Consequential Amendments) Act 2007 .\n\n2. Commencement\n    This Act commences on a day to be proclaimed.\n\n3.\n    See Schedule 1 .\n\n4. Effect of certain consequential amendments\n    The amendment by this Act of a provision of any regulations, rules or by-laws made under any Act does not prevent that provision or any other provision of those regulations, rules or by-laws from being amended or rescinded by any subsequent regulations, rules or by-laws.\n\nSCHEDULE 1 - Consequential Amendments\n\nThe amendments effected by Section 3 and this Schedule have been incorporated into the authorised version of the appropriate Acts and Statutory Rules."
}